torchcodec-0.8.0.dist-info/RECORD
torchcodec-0.8.0.dist-info/WHEEL
torchcodec-0.8.0.dist-info/top_level.txt
torchcodec-0.8.0.dist-info/METADATA
torchcodec-0.8.0.dist-info/licenses/LICENSE
torchcodec/libtorchcodec_core6.dylib
torchcodec/version.py
torchcodec/libtorchcodec_core4.dylib
torchcodec/libtorchcodec_pybind_ops4.so
torchcodec/libtorchcodec_custom_ops8.dylib
torchcodec/__init__.py
torchcodec/libtorchcodec_core5.dylib
torchcodec/libtorchcodec_core7.dylib
torchcodec/libtorchcodec_pybind_ops5.so
torchcodec/libtorchcodec_pybind_ops6.so
torchcodec/libtorchcodec_custom_ops4.dylib
torchcodec/libtorchcodec_pybind_ops7.so
torchcodec/libtorchcodec_custom_ops6.dylib
torchcodec/libtorchcodec_core8.dylib
torchcodec/_frame.py
torchcodec/libtorchcodec_pybind_ops8.so
torchcodec/libtorchcodec_custom_ops7.dylib
torchcodec/_internally_replaced_utils.py
torchcodec/libtorchcodec_custom_ops5.dylib
torchcodec/_core/custom_ops.cpp
torchcodec/_core/AVIOContextHolder.h
torchcodec/_core/FFMPEGCommon.cpp
torchcodec/_core/_metadata.py
torchcodec/_core/CudaDeviceInterface.h
torchcodec/_core/Frame.cpp
torchcodec/_core/ValidationUtils.h
torchcodec/_core/CMakeLists.txt
torchcodec/_core/NVDECCache.cpp
torchcodec/_core/BetaCudaDeviceInterface.cpp
torchcodec/_core/CUDACommon.cpp
torchcodec/_core/StreamOptions.h
torchcodec/_core/AVIOContextHolder.cpp
torchcodec/_core/AVIOFileLikeContext.h
torchcodec/_core/AVIOFileLikeContext.cpp
torchcodec/_core/FFMPEGCommon.h
torchcodec/_core/Frame.h
torchcodec/_core/SingleStreamDecoder.h
torchcodec/_core/Cache.h
torchcodec/_core/BetaCudaDeviceInterface.h
torchcodec/_core/__init__.py
torchcodec/_core/ValidationUtils.cpp
torchcodec/_core/Metadata.h
torchcodec/_core/FilterGraph.cpp
torchcodec/_core/ops.py
torchcodec/_core/CpuDeviceInterface.h
torchcodec/_core/CudaDeviceInterface.cpp
torchcodec/_core/Transform.cpp
torchcodec/_core/NVDECCache.h
torchcodec/_core/Encoder.h
torchcodec/_core/AVIOTensorContext.cpp
torchcodec/_core/Transform.h
torchcodec/_core/fetch_and_expose_non_gpl_ffmpeg_libs.cmake
torchcodec/_core/CUDACommon.h
torchcodec/_core/AVIOTensorContext.h
