Metadata-Version: 2.4
Name: torchcodec
Version: 0.8.0
Summary: A video decoder for PyTorch
Author-email: PyTorch Team <packages@pytorch.org>
Project-URL: GitHub, https://github.com/pytorch/torchcodec
Project-URL: Documentation, https://pytorch.org/torchcodec/stable/index.html
Requires-Python: >=3.8
License-File: LICENSE
Provides-Extra: dev
Requires-Dist: numpy; extra == "dev"
Requires-Dist: pytest; extra == "dev"
Requires-Dist: pillow; extra == "dev"
Dynamic: license-file
